django_pyp8s/__init__.py
django_pyp8s/_version.py
django_pyp8s/apps.py
django_pyp8s/urls.py
django_pyp8s/migrations/__init__.py
django_pyp8s/views/__init__.py
django_pyp8s/views/internal.py
django_pyp8s-1.0.0.dist-info/LICENSE
django_pyp8s-1.0.0.dist-info/METADATA
django_pyp8s-1.0.0.dist-info/WHEEL
django_pyp8s-1.0.0.dist-info/top_level.txt
django_pyp8s-1.0.0.dist-info/RECORD
