Metadata-Version: 2.1
Name: django-pyp8s
Version: 1.0.0
Summary: Django application that provides an interface to pyp8s metrics collector
Home-page: https://github.com/pyp8s/django-pyp8s
Author: Pavel Kim
Author-email: hello@pavelkim.com
Classifier: License :: OSI Approved :: GNU General Public License v3 (GPLv3)
Classifier: Operating System :: OS Independent
Classifier: Programming Language :: Python
Classifier: Programming Language :: Python :: 3
Classifier: Framework :: Django
Classifier: Framework :: Django :: 4
Classifier: Topic :: Internet :: WWW/HTTP
Classifier: Topic :: Internet :: WWW/HTTP :: Dynamic Content
Requires-Python: >=3.6
License-File: LICENSE
Requires-Dist: pyp8s (>=3.2.0)
Requires-Dist: Django (>=4.0)
